dogonnet/__init__.py
dogonnet/py.typed
dogonnet/cli/__init__.py
dogonnet/cli/main.py
dogonnet/client/__init__.py
dogonnet/client/dashboard.py
dogonnet/lib/__init__.py
dogonnet/lib/layouts.libsonnet
dogonnet/lib/main.libsonnet
dogonnet/lib/presets.libsonnet
dogonnet/lib/widgets.libsonnet
dogonnet/utils/__init__.py
dogonnet/utils/jsonnet.py
dogonnet-0.1.1.dist-info/licenses/LICENSE
dogonnet-0.1.1.dist-info/METADATA
dogonnet-0.1.1.dist-info/WHEEL
dogonnet-0.1.1.dist-info/entry_points.txt
dogonnet-0.1.1.dist-info/top_level.txt
dogonnet-0.1.1.dist-info/RECORD
