Metadata-Version: 2.4
Name: dogonnet
Version: 0.1.1
Summary: AI-friendly Datadog dashboard templating library using Jsonnet - create beautiful dashboards from natural language
Author-email: Metta AI <team@metta.ai>
License: MIT
Project-URL: Homepage, https://github.com/rjwalters/dogonnet
Project-URL: Documentation, https://github.com/rjwalters/dogonnet#readme
Project-URL: Repository, https://github.com/rjwalters/dogonnet
Project-URL: Issues, https://github.com/rjwalters/dogonnet/issues
Keywords: datadog,jsonnet,dashboards,monitoring,observability,sre,devops,infrastructure-as-code,iac,llm,ai,claude,chatgpt,golden-signals,metrics,visualization
Classifier: Development Status :: 3 - Alpha
Classifier: Intended Audience :: Developers
Classifier: Intended Audience :: System Administrators
Classifier: License :: OSI Approved :: MIT License
Classifier: Programming Language :: Python :: 3
Classifier: Programming Language :: Python :: 3.10
Classifier: Programming Language :: Python :: 3.11
Classifier: Programming Language :: Python :: 3.12
Classifier: Programming Language :: Python :: 3.13
Classifier: Topic :: Software Development :: Code Generators
Classifier: Topic :: Software Development :: Libraries :: Python Modules
Classifier: Topic :: System :: Monitoring
Classifier: Topic :: System :: Systems Administration
Classifier: Operating System :: OS Independent
Classifier: Typing :: Typed
Requires-Python: >=3.10
License-File: LICENSE
Requires-Dist: click>=8.0.0
Requires-Dist: rich>=13.0.0
Requires-Dist: requests>=2.28.0
Requires-Dist: jsonnet>=0.20.0
Provides-Extra: dev
Requires-Dist: pytest>=7.0.0; extra == "dev"
Requires-Dist: pytest-cov>=4.0.0; extra == "dev"
Requires-Dist: ruff>=0.1.0; extra == "dev"
Requires-Dist: mypy>=1.0.0; extra == "dev"
Dynamic: license-file
